qgrid/__init__.py
qgridnext/__init__.py
qgridnext/_version.py
qgridnext/grid.py
qgridnext/tests/__init__.py
qgridnext/tests/test_grid.py
qgridnext-2.0.4.data/data/etc/jupyter/nbconfig/notebook.d/qgridnext.json
qgridnext-2.0.4.data/data/share/jupyter/labextensions/qgridnext/install.json
qgridnext-2.0.4.data/data/share/jupyter/labextensions/qgridnext/package.json
qgridnext-2.0.4.data/data/share/jupyter/labextensions/qgridnext/static/0334d95f192293133bff.png
qgridnext-2.0.4.data/data/share/jupyter/labextensions/qgridnext/static/29.155d6c922874bc40130c.js
qgridnext-2.0.4.data/data/share/jupyter/labextensions/qgridnext/static/29.155d6c922874bc40130c.js.LICENSE.txt
qgridnext-2.0.4.data/data/share/jupyter/labextensions/qgridnext/static/3323f9811f1e48bb9ff6.gif
qgridnext-2.0.4.data/data/share/jupyter/labextensions/qgridnext/static/358.69f5c3a2cee42caf4d40.js
qgridnext-2.0.4.data/data/share/jupyter/labextensions/qgridnext/static/5f0f36454a984a990d18.gif
qgridnext-2.0.4.data/data/share/jupyter/labextensions/qgridnext/static/5f992effff4100c7e775.png
qgridnext-2.0.4.data/data/share/jupyter/labextensions/qgridnext/static/634d05f83eaccc102de8.gif
qgridnext-2.0.4.data/data/share/jupyter/labextensions/qgridnext/static/692.c43185db45ea2ca21215.js
qgridnext-2.0.4.data/data/share/jupyter/labextensions/qgridnext/static/692.c43185db45ea2ca21215.js.LICENSE.txt
qgridnext-2.0.4.data/data/share/jupyter/labextensions/qgridnext/static/78555fcb75ea44debb5e.png
qgridnext-2.0.4.data/data/share/jupyter/labextensions/qgridnext/static/7d4b7e878161625bae04.png
qgridnext-2.0.4.data/data/share/jupyter/labextensions/qgridnext/static/820.c4c9fee0e440d174acb8.js
qgridnext-2.0.4.data/data/share/jupyter/labextensions/qgridnext/static/884.27365c66da3d30fd7a72.js
qgridnext-2.0.4.data/data/share/jupyter/labextensions/qgridnext/static/8e0f2944c6b9f7c98884.png
qgridnext-2.0.4.data/data/share/jupyter/labextensions/qgridnext/static/921.d14dca89e63909633fd7.js
qgridnext-2.0.4.dist-info/LICENSE
qgridnext-2.0.4.dist-info/METADATA
qgridnext-2.0.4.dist-info/WHEEL
qgridnext-2.0.4.dist-info/top_level.txt
qgridnext-2.0.4.dist-info/RECORD
