Metadata-Version: 2.1
Name: qgridnext
Version: 2.0.4
Summary: An Interactive Grid for Sorting and Filtering DataFrames in Jupyter
Home-page: https://github.com/zhihanyue/qgridnext
Author: QgridNext
License: Apache-2.0
Keywords: ipython,jupyter,widgets
Classifier: Intended Audience :: Developers
Classifier: Intended Audience :: Science/Research
Classifier: Topic :: Office/Business :: Financial
Classifier: Topic :: Scientific/Engineering :: Information Analysis
Classifier: Topic :: Multimedia :: Graphics
Classifier: Framework :: Jupyter
Classifier: Framework :: Jupyter :: JupyterLab
Classifier: Framework :: Jupyter :: JupyterLab :: 4
Classifier: Framework :: Jupyter :: JupyterLab :: Extensions
Classifier: Framework :: Jupyter :: JupyterLab :: Extensions :: Prebuilt
Classifier: Programming Language :: Python :: 3
Classifier: Programming Language :: Python :: 3.7
Classifier: Programming Language :: Python :: 3.8
Classifier: Programming Language :: Python :: 3.9
Classifier: Programming Language :: Python :: 3.10
Classifier: Programming Language :: Python :: 3.11
Requires-Python: >=3.7
License-File: LICENSE
Requires-Dist: pandas >=0.20.0
Requires-Dist: ipywidgets >=7.0.0
Requires-Dist: numpy
Requires-Dist: traitlets
Provides-Extra: test
Requires-Dist: pytest >=2.8.5 ; extra == 'test'
Requires-Dist: flake8 >=3.6.0 ; extra == 'test'
